torch2onnx2trt/__init__.py
torch2onnx2trt/main.py
torch2onnx2trt/utils.py
torch2onnx2trt/tests/__init__.py
torch2onnx2trt/tests/test_conversion.py
torch2onnx2trt-0.1.2.dist-info/LICENSE
torch2onnx2trt-0.1.2.dist-info/METADATA
torch2onnx2trt-0.1.2.dist-info/WHEEL
torch2onnx2trt-0.1.2.dist-info/top_level.txt
torch2onnx2trt-0.1.2.dist-info/RECORD
