Metadata-Version: 2.1
Name: torch2onnx2trt
Version: 0.1.2
Summary: A simple package that wraps PyTorch models conversion to ONNX and TensorRT
Home-page: https://github.com/ucLh/torch2onnx2trt
Author: Vladimir Luchinskiy
Author-email: 
License: MIT
Platform: UNKNOWN
Requires-Dist: onnx (>=1.9.0)
Requires-Dist: onnx-simplifier (>=0.3.6)
